pytore/__init__.py
pytore/math.py
pytore-0.0.1.dist-info/LICENSE
pytore-0.0.1.dist-info/METADATA
pytore-0.0.1.dist-info/WHEEL
pytore-0.0.1.dist-info/top_level.txt
pytore-0.0.1.dist-info/RECORD
