Metadata-Version: 2.1
Name: pytore
Version: 0.0.1
Summary: Helper package for university education.
Author: birgis (Tore Birgisson
Author-email: <mail@birgisson.no
Keywords: python
Classifier: Development Status :: 1 - Planning
Classifier: Intended Audience :: Developers
Classifier: Programming Language :: Python :: 3
Classifier: Operating System :: Unix
Classifier: Operating System :: MacOS :: MacOS X
Classifier: Operating System :: Microsoft :: Windows
License-File: LICENSE
